joule_sdk/__init__.py
joule_sdk/anthropic_wrapper.py
joule_sdk/client.py
joule_sdk/openai_wrapper.py
joule_sdk/pricing.py
joule_sdk-0.1.0.dist-info/METADATA
joule_sdk-0.1.0.dist-info/WHEEL
joule_sdk-0.1.0.dist-info/top_level.txt
joule_sdk-0.1.0.dist-info/RECORD
